_quickfix.cpython-39-x86_64-linux-gnu.so
quickfix.py
quickfix40.py
quickfix41.py
quickfix42.py
quickfix43.py
quickfix44.py
quickfix50.py
quickfix50sp1.py
quickfix50sp2.py
quickfixt11.py
quickfix2-1.0.2.data/data/share/quickfix/FIX40.xml
quickfix2-1.0.2.data/data/share/quickfix/FIX41.xml
quickfix2-1.0.2.data/data/share/quickfix/FIX42.xml
quickfix2-1.0.2.data/data/share/quickfix/FIX43.xml
quickfix2-1.0.2.data/data/share/quickfix/FIX44.xml
quickfix2-1.0.2.data/data/share/quickfix/FIX50.xml
quickfix2-1.0.2.data/data/share/quickfix/FIX50SP1.xml
quickfix2-1.0.2.data/data/share/quickfix/FIX50SP2.xml
quickfix2-1.0.2.data/data/share/quickfix/FIXT11.xml
quickfix2-1.0.2.dist-info/LICENSE
quickfix2-1.0.2.dist-info/METADATA
quickfix2-1.0.2.dist-info/WHEEL
quickfix2-1.0.2.dist-info/top_level.txt
quickfix2-1.0.2.dist-info/RECORD
