Metadata-Version: 2.2
Name: quickfix2
Version: 1.0.2
Summary: FIX (Financial Information eXchange) protocol implementation; original author: Oren Miller, oren@quickfixengine.org
Maintainer: Oren Miller
Maintainer-email: oren@quickfixengine.org
License: The QuickFIX Software License, Version 1.0
License-File: LICENSE
Dynamic: description
Dynamic: description-content-type
Dynamic: license
Dynamic: maintainer
Dynamic: maintainer-email
Dynamic: summary
